{
 "cells": [
  {
   "attachments": {},
   "cell_type": "markdown",
   "metadata": {},
   "source": [
    "This is just a script for generating VM steps for a beamer"
   ]
  },
  {
   "cell_type": "code",
   "execution_count": 10,
   "metadata": {},
   "outputs": [],
   "source": [
    "bytecode = '''\n",
    "  2           0 LOAD_CONST               1 (0)\n",
    "              2 STORE_FAST               2 (a0)\n",
    "\n",
    "  3           4 LOAD_CONST               2 (1)\n",
    "              6 STORE_FAST               3 (a1)\n",
    "\n",
    "  4           8 LOAD_CONST               3 (2)\n",
    "             10 STORE_FAST               4 (a2)\n",
    "\n",
    "  5          12 LOAD_FAST                2 (a0)\n",
    "             14 LOAD_FAST                3 (a1)\n",
    "             16 BINARY_ADD\n",
    "             18 LOAD_FAST                4 (a2)\n",
    "             20 BINARY_ADD\n",
    "             22 STORE_FAST               5 (a3)\n",
    "\n",
    "  6          24 LOAD_FAST                0 (a)\n",
    "             26 LOAD_METHOD              0 (sum)\n",
    "             28 CALL_METHOD              0\n",
    "             30 LOAD_CONST               1 (0)\n",
    "             32 COMPARE_OP               4 (>)\n",
    "             34 POP_JUMP_IF_FALSE       48\n",
    "\n",
    "  7          36 LOAD_FAST                0 (a)\n",
    "             38 LOAD_FAST                1 (b)\n",
    "             40 BINARY_ADD\n",
    "             42 LOAD_FAST                5 (a3)\n",
    "             44 BINARY_ADD\n",
    "             46 RETURN_VALUE\n",
    "\n",
    "  8     >>   48 LOAD_FAST                0 (a)\n",
    "             50 LOAD_FAST                1 (b)\n",
    "             52 BINARY_SUBTRACT\n",
    "             54 RETURN_VALUE\n",
    "'''.strip()"
   ]
  },
  {
   "cell_type": "code",
   "execution_count": 11,
   "metadata": {},
   "outputs": [],
   "source": [
    "def get_hightlight_lineno():\n",
    "    for no,line in enumerate(bytecode.split('\\n')):\n",
    "        line = line.strip()\n",
    "        if not line: continue\n",
    "        fs = line.split()\n",
    "        instr_no = -1\n",
    "\n",
    "        if len(fs) == 5:\n",
    "            instr_no = fs[1]\n",
    "        elif len(fs) == 4:\n",
    "            instr_no = fs[0]\n",
    "        elif len(fs) == 6:\n",
    "            instr_no = fs[2]\n",
    "        elif len(fs) == 2:\n",
    "            instr_no = fs[0]\n",
    "        elif len(fs) == 3:\n",
    "            instr_no = fs[0]\n",
    "        else:\n",
    "            print(fs)\n",
    "            raise\n",
    "\n",
    "        yield instr_no, no"
   ]
  },
  {
   "cell_type": "code",
   "execution_count": 12,
   "metadata": {},
   "outputs": [],
   "source": [
    "from dataclasses import dataclass\n",
    "from typing import *\n",
    "\n",
    "@dataclass\n",
    "class Record:\n",
    "    highlight_no:int\n",
    "    instr_no: str\n",
    "    stack: List[str]\n",
    "    annotation: List[str]\n",
    "    subgraph: List[str]\n",
    "    step: int"
   ]
  },
  {
   "cell_type": "code",
   "execution_count": 13,
   "metadata": {},
   "outputs": [],
   "source": [
    "def get_block(record:Record):\n",
    "    return \"\"\"\n",
    "    ** Tracing on a simple case (step {step}) :B_block:\n",
    ":PROPERTIES:\n",
    ":BEAMER_env: block\n",
    ":BEAMER_opt: fragile\n",
    ":END:\n",
    "*** C :B_columns:\n",
    ":PROPERTIES:\n",
    ":BEAMER_opt: t\n",
    ":BEAMER_env: columns\n",
    ":END:\n",
    "**** Tracing the bytecode :BMCOL:\n",
    ":PROPERTIES:\n",
    ":BEAMER_col: 0.5\n",
    ":END:\n",
    "\n",
    "\\\\tiny\n",
    "#+BEGIN_SRC latex\n",
    "\\\\begin{{minted}}[highlightlines={highlight_no}, highlightcolor=pink]{{python}}\n",
    "  2           0 LOAD_CONST               1 (0)\n",
    "              2 STORE_FAST               2 (a0)\n",
    "\n",
    "  3           4 LOAD_CONST               2 (1)\n",
    "              6 STORE_FAST               3 (a1)\n",
    "\n",
    "  4           8 LOAD_CONST               3 (2)\n",
    "             10 STORE_FAST               4 (a2)\n",
    "\n",
    "  5          12 LOAD_FAST                2 (a0)\n",
    "             14 LOAD_FAST                3 (a1)\n",
    "             16 BINARY_ADD\n",
    "             18 LOAD_FAST                4 (a2)\n",
    "             20 BINARY_ADD\n",
    "             22 STORE_FAST               5 (a3)\n",
    "\n",
    "  6          24 LOAD_FAST                0 (a)\n",
    "             26 LOAD_METHOD              0 (sum)\n",
    "             28 CALL_METHOD              0\n",
    "             30 LOAD_CONST               1 (0)\n",
    "             32 COMPARE_OP               4 (>)\n",
    "             34 POP_JUMP_IF_FALSE       48\n",
    "\n",
    "  7          36 LOAD_FAST                0 (a)\n",
    "             38 LOAD_FAST                1 (b)\n",
    "             40 BINARY_ADD\n",
    "             42 LOAD_FAST                5 (a3)\n",
    "             44 BINARY_ADD\n",
    "             46 RETURN_VALUE\n",
    "\n",
    "  8     >>   48 LOAD_FAST                0 (a)\n",
    "             50 LOAD_FAST                1 (b)\n",
    "             52 BINARY_SUBTRACT\n",
    "             54 RETURN_VALUE\n",
    "\\\\end{{minted}}\n",
    "#+END_SRC\n",
    "\n",
    "\n",
    "**** States :B_block:BMCOL:\n",
    ":PROPERTIES:\n",
    ":BEAMER_col: 0.5\n",
    ":BEAMER_opt: t\n",
    ":BEAMER_env: block\n",
    ":END:\n",
    "\n",
    "{annotation}\n",
    "\n",
    "***** Instruction counter\n",
    "\\small\n",
    "\n",
    "{instr_no}\n",
    "\n",
    "\n",
    "\n",
    "***** Frame stack\n",
    ":PROPERTIES:\n",
    ":BEAMER_env: block\n",
    ":END:\n",
    "\\small\n",
    "|---+--------|\n",
    "| id | values |\n",
    "|---+--------|\n",
    "{stack}\n",
    "\n",
    "\n",
    "\n",
    "***** Output graph :B_block:\n",
    ":PROPERTIES:\n",
    ":BEAMER_env: block\n",
    ":END:\n",
    "\\\\tiny\n",
    "\n",
    "|---+-----|\n",
    "|  id | ops |\n",
    "|---+-----|\n",
    "{subgraph}\n",
    "\n",
    "\n",
    "\n",
    "\"\"\".format(\n",
    "    step=record.step,\n",
    "    highlight_no=record.highlight_no+1,\n",
    "    annotation='\\n'.join(record.annotation) if type(record.annotation) == list else record.annotation,\n",
    "instr_no=record.instr_no,\n",
    "stack = '\\n'.join([\"| %d | ~%s~ |\" % (no,item) for no, item in enumerate(record.stack)]),\n",
    "subgraph = '\\n'.join([\"| %d | ~%s~ |\" % (no,item) for no, item in enumerate(record.subgraph)]),\n",
    ").lstrip()\n"
   ]
  },
  {
   "cell_type": "code",
   "execution_count": 14,
   "metadata": {},
   "outputs": [
    {
     "name": "stdout",
     "output_type": "stream",
     "text": [
      "[('0', 0), ('2', 1), ('4', 3), ('6', 4), ('8', 6), ('10', 7), ('12', 9), ('14', 10), ('16', 11), ('18', 12), ('20', 13), ('22', 14), ('24', 16), ('26', 17), ('28', 18), ('30', 19), ('32', 20), ('34', 21), ('36', 23), ('38', 24), ('40', 25), ('42', 26), ('44', 27), ('46', 28), ('48', 30), ('50', 31), ('52', 32), ('54', 33)]\n"
     ]
    },
    {
     "data": {
      "text/plain": [
       "28"
      ]
     },
     "execution_count": 14,
     "metadata": {},
     "output_type": "execute_result"
    }
   ],
   "source": [
    "steps = [x for x in get_hightlight_lineno()]\n",
    "print(steps)\n",
    "len(steps)\n",
    "#get_hightlight_lineno()"
   ]
  },
  {
   "cell_type": "code",
   "execution_count": 15,
   "metadata": {},
   "outputs": [],
   "source": [
    "records = []\n",
    "step = 0\n",
    "\n",
    "# a0 = 0\n",
    "records.append(Record(\n",
    "    highlight_no=steps[step][1],\n",
    "    instr_no=steps[step][0],\n",
    "    step=step,\n",
    "    stack=['ConstantValue(0)'],\n",
    "    subgraph=[\"%a : torch.Tensor [#users=0] = placeholder[target=a]\",\n",
    "              \"%b : torch.Tensor [#users=0] = placeholder[target=b]\",\n",
    "              ],\n",
    "    annotation=\"Load a constant, push it on the stack\",\n",
    "))\n",
    "step += 1\n",
    "records.append(Record(\n",
    "    highlight_no=steps[step][1],\n",
    "    instr_no=steps[step][0],\n",
    "    step=step,\n",
    "    stack=[],\n",
    "    subgraph=[\"%a : torch.Tensor [#users=0] = placeholder[target=a]\",\n",
    "              \"%b : torch.Tensor [#users=0] = placeholder[target=b]\", ],\n",
    "    annotation=\"Store to local variable a0\",\n",
    "))\n",
    "step += 1\n",
    "\n",
    "# a1 = 1\n",
    "records.append(Record(\n",
    "    highlight_no=steps[step][1],\n",
    "    instr_no=steps[step][0],\n",
    "    step=step,\n",
    "    stack=['ConstantValue(1)'],\n",
    "    subgraph=[\"%a : torch.Tensor [#users=0] = placeholder[target=a]\",\n",
    "              \"%b : torch.Tensor [#users=0] = placeholder[target=b]\", ],\n",
    "    annotation=\"Load a constant, push it on the stack\",\n",
    "))\n",
    "step += 1\n",
    "records.append(Record(\n",
    "    highlight_no=steps[step][1],\n",
    "    instr_no=steps[step][0],\n",
    "    step=step,\n",
    "    stack=[],\n",
    "    subgraph=[\"%a : torch.Tensor [#users=0] = placeholder[target=a]\",\n",
    "              \"%b : torch.Tensor [#users=0] = placeholder[target=b]\", ],\n",
    "    annotation=\"Store to local variable a1\",\n",
    "))\n",
    "step += 1\n",
    "\n",
    "\n",
    "# a2 = 2\n",
    "records.append(Record(\n",
    "    highlight_no=steps[step][1],\n",
    "    instr_no=steps[step][0],\n",
    "    step=step,\n",
    "    stack=['ConstantValue(2)'],\n",
    "    subgraph=[\"%a : torch.Tensor [#users=0] = placeholder[target=a]\",\n",
    "              \"%b : torch.Tensor [#users=0] = placeholder[target=b]\", ],\n",
    "    annotation=\"Load a constant, push it on the stack\",\n",
    "))\n",
    "step += 1\n",
    "records.append(Record(\n",
    "    highlight_no=steps[step][1],\n",
    "    instr_no=steps[step][0],\n",
    "    step=step,\n",
    "    stack=[],\n",
    "    subgraph=[\"%a : torch.Tensor [#users=0] = placeholder[target=a]\",\n",
    "              \"%b : torch.Tensor [#users=0] = placeholder[target=b]\", ],\n",
    "    annotation=\"Store to local variable a2\",\n",
    "))\n",
    "step += 1"
   ]
  },
  {
   "cell_type": "code",
   "execution_count": 16,
   "metadata": {},
   "outputs": [],
   "source": [
    "# a3 = a0 + a1 + a2\n",
    "records.append(Record(\n",
    "    highlight_no=steps[step][1],\n",
    "    instr_no=steps[step][0],\n",
    "    step=step,\n",
    "    stack=['ConstantValue(a0)'],\n",
    "    subgraph=[\"%a : torch.Tensor [#users=0] = placeholder[target=a]\",\n",
    "              \"%b : torch.Tensor [#users=0] = placeholder[target=b]\", ],\n",
    "    annotation=\"Load a constant, push it on the stack\",\n",
    "))\n",
    "step += 1\n",
    "records.append(Record(\n",
    "    highlight_no=steps[step][1],\n",
    "    instr_no=steps[step][0],\n",
    "    step=step,\n",
    "    stack=['ConstantValue(a0)', 'ConstantValue(a1)'],\n",
    "    subgraph=[\"%a : torch.Tensor [#users=0] = placeholder[target=a]\",\n",
    "              \"%b : torch.Tensor [#users=0] = placeholder[target=b]\", ],\n",
    "    annotation=\"Load a constant, push it on the stack\",\n",
    "))\n",
    "step += 1\n",
    "records.append(Record( # BINARY_ADD\n",
    "    highlight_no=steps[step][1],\n",
    "    instr_no=steps[step][0],\n",
    "    step=step,\n",
    "    stack=['ConstantValue(1)'],\n",
    "    subgraph=[\"%a : torch.Tensor [#users=0] = placeholder[target=a]\",\n",
    "              \"%b : torch.Tensor [#users=0] = placeholder[target=b]\", ],\n",
    "    annotation=\"\",\n",
    "))\n",
    "step += 1\n",
    "\n",
    "records.append(Record(\n",
    "    highlight_no=steps[step][1],\n",
    "    instr_no=steps[step][0],\n",
    "    step=step,\n",
    "    stack=['ConstantValue(1)', 'ConstantValue(a2)'],\n",
    "    subgraph=[\"%a : torch.Tensor [#users=0] = placeholder[target=a]\",\n",
    "              \"%b : torch.Tensor [#users=0] = placeholder[target=b]\", ],\n",
    "    annotation=\"Load a constant, push it on the stack\",\n",
    "))\n",
    "step += 1\n",
    "\n",
    "records.append(Record( # BINARY_ADD\n",
    "    highlight_no=steps[step][1],\n",
    "    instr_no=steps[step][0],\n",
    "    step=step,\n",
    "    stack=['ConstantValue(3)',],\n",
    "    subgraph=[\"%a : torch.Tensor [#users=0] = placeholder[target=a]\",\n",
    "              \"%b : torch.Tensor [#users=0] = placeholder[target=b]\", ],\n",
    "    annotation=\"\",\n",
    "))\n",
    "step += 1\n",
    "\n",
    "# STORE_FAST a3\n",
    "records.append(Record(\n",
    "    highlight_no=steps[step][1],\n",
    "    instr_no=steps[step][0],\n",
    "    step=step,\n",
    "    stack=[],\n",
    "    subgraph=[\"%a : torch.Tensor [#users=0] = placeholder[target=a]\",\n",
    "              \"%b : torch.Tensor [#users=0] = placeholder[target=b]\", ],\n",
    "    annotation=\"\",\n",
    "))\n",
    "step += 1\n"
   ]
  },
  {
   "cell_type": "code",
   "execution_count": 17,
   "metadata": {},
   "outputs": [],
   "source": [
    "# LOAD_FAST (a)\n",
    "records.append(Record(\n",
    "    highlight_no=steps[step][1],\n",
    "    instr_no=steps[step][0],\n",
    "    step=step,\n",
    "    stack=['TensorVariable(a)',],\n",
    "    subgraph=[\"%a : torch.Tensor [#users=0] = placeholder[target=a]\",\n",
    "              \"%b : torch.Tensor [#users=0] = placeholder[target=b]\", ],\n",
    "    annotation=\"Load a tensor, push to stack\",\n",
    "))\n",
    "step += 1\n",
    "\n",
    "# LOAD_METHOD\n",
    "records.append(Record(\n",
    "    highlight_no=steps[step][1],\n",
    "    instr_no=steps[step][0],\n",
    "    step=step,\n",
    "    stack=['TensorVariable(a)', 'GetAttrVariable(TensorVariable(), sum)'],\n",
    "    subgraph=[\"%a : torch.Tensor [#users=0] = placeholder[target=a]\",\n",
    "              \"%b : torch.Tensor [#users=0] = placeholder[target=b]\", ],\n",
    "    annotation=\"\",\n",
    "))\n",
    "step += 1\n",
    "\n",
    "\n",
    "# CALL_METHOD\n",
    "records.append(Record(\n",
    "    highlight_no=steps[step][1],\n",
    "    instr_no=steps[step][0],\n",
    "    step=step,\n",
    "    stack=['TensorVariable()'],\n",
    "    subgraph=[\"%a : torch.Tensor [#users=0] = placeholder[target=a]\",\n",
    "              \"%b : torch.Tensor [#users=0] = placeholder[target=b]\", \n",
    "              \"%sum_1 : [#users=0] = call_method[target=sum](args = (%a,), kwargs = {})\",\n",
    "              ],\n",
    "    annotation=\"\",\n",
    "))\n",
    "step += 1\n",
    "\n",
    "# LOAD_CONST\n",
    "records.append(Record(\n",
    "    highlight_no=steps[step][1],\n",
    "    instr_no=steps[step][0],\n",
    "    step=step,\n",
    "    stack=['TensorVariable()', 'ConstantValue(0)'],\n",
    "    subgraph=[\"%a : torch.Tensor [#users=0] = placeholder[target=a]\",\n",
    "              \"%b : torch.Tensor [#users=0] = placeholder[target=b]\", \n",
    "              \"%sum_1 : [#users=0] = call_method[target=sum](args = (%a,), kwargs = {})\",\n",
    "              ],\n",
    "    annotation=\"\",\n",
    "))\n",
    "step += 1\n",
    "\n",
    "\n",
    "# COMPARE_OP\n",
    "records.append(Record(\n",
    "    highlight_no=steps[step][1],\n",
    "    instr_no=steps[step][0],\n",
    "    step=step,\n",
    "    stack=['TensorVariable()'],\n",
    "    subgraph=[\"%a : torch.Tensor [#users=0] = placeholder[target=a]\",\n",
    "              \"%b : torch.Tensor [#users=0] = placeholder[target=b]\", \n",
    "              \"%sum_1 : [#users=0] = call_method[target=sum](args = (%a,), kwargs = {})\",\n",
    "              \"%gt : [#users=0] = call_method[target=gt](args = (%sum_1, 0), kwargs = {})\",\n",
    "              ],\n",
    "    annotation=\"\",\n",
    "))\n",
    "step += 1\n",
    "\n",
    "\n",
    "# JUMP_IF_FALSE\n",
    "records.append(Record(\n",
    "    highlight_no=steps[step][1],\n",
    "    instr_no=steps[step][0],\n",
    "    step=step,\n",
    "    stack=[],\n",
    "    subgraph=[ ],\n",
    "    annotation=[\"TensorVariable as condition, trigger compile subgraph\",\n",
    "                \"Follows the heuristics of ~generic_jump()~\"],\n",
    "))\n",
    "step += 1\n",
    "\n",
    "\n",
    "\n"
   ]
  },
  {
   "cell_type": "code",
   "execution_count": 18,
   "metadata": {},
   "outputs": [
    {
     "name": "stdout",
     "output_type": "stream",
     "text": [
      "** Tracing on a simple case (step 0) :B_block:\n",
      ":PROPERTIES:\n",
      ":BEAMER_env: block\n",
      ":BEAMER_opt: fragile\n",
      ":END:\n",
      "*** C :B_columns:\n",
      ":PROPERTIES:\n",
      ":BEAMER_opt: t\n",
      ":BEAMER_env: columns\n",
      ":END:\n",
      "**** Tracing the bytecode :BMCOL:\n",
      ":PROPERTIES:\n",
      ":BEAMER_col: 0.5\n",
      ":END:\n",
      "\n",
      "\\tiny\n",
      "#+BEGIN_SRC latex\n",
      "\\begin{minted}[highlightlines=1, highlightcolor=pink]{python}\n",
      "  2           0 LOAD_CONST               1 (0)\n",
      "              2 STORE_FAST               2 (a0)\n",
      "\n",
      "  3           4 LOAD_CONST               2 (1)\n",
      "              6 STORE_FAST               3 (a1)\n",
      "\n",
      "  4           8 LOAD_CONST               3 (2)\n",
      "             10 STORE_FAST               4 (a2)\n",
      "\n",
      "  5          12 LOAD_FAST                2 (a0)\n",
      "             14 LOAD_FAST                3 (a1)\n",
      "             16 BINARY_ADD\n",
      "             18 LOAD_FAST                4 (a2)\n",
      "             20 BINARY_ADD\n",
      "             22 STORE_FAST               5 (a3)\n",
      "\n",
      "  6          24 LOAD_FAST                0 (a)\n",
      "             26 LOAD_METHOD              0 (sum)\n",
      "             28 CALL_METHOD              0\n",
      "             30 LOAD_CONST               1 (0)\n",
      "             32 COMPARE_OP               4 (>)\n",
      "             34 POP_JUMP_IF_FALSE       48\n",
      "\n",
      "  7          36 LOAD_FAST                0 (a)\n",
      "             38 LOAD_FAST                1 (b)\n",
      "             40 BINARY_ADD\n",
      "             42 LOAD_FAST                5 (a3)\n",
      "             44 BINARY_ADD\n",
      "             46 RETURN_VALUE\n",
      "\n",
      "  8     >>   48 LOAD_FAST                0 (a)\n",
      "             50 LOAD_FAST                1 (b)\n",
      "             52 BINARY_SUBTRACT\n",
      "             54 RETURN_VALUE\n",
      "\\end{minted}\n",
      "#+END_SRC\n",
      "\n",
      "\n",
      "**** States :B_block:BMCOL:\n",
      ":PROPERTIES:\n",
      ":BEAMER_col: 0.5\n",
      ":BEAMER_opt: t\n",
      ":BEAMER_env: block\n",
      ":END:\n",
      "\n",
      "Load a constant, push it on the stack\n",
      "\n",
      "***** Instruction counter\n",
      "\\small\n",
      "\n",
      "0\n",
      "\n",
      "\n",
      "\n",
      "***** Frame stack\n",
      ":PROPERTIES:\n",
      ":BEAMER_env: block\n",
      ":END:\n",
      "\\small\n",
      "|---+--------|\n",
      "| id | values |\n",
      "|---+--------|\n",
      "| 0 | ~ConstantValue(0)~ |\n",
      "\n",
      "\n",
      "\n",
      "***** Output graph :B_block:\n",
      ":PROPERTIES:\n",
      ":BEAMER_env: block\n",
      ":END:\n",
      "\\tiny\n",
      "\n",
      "|---+-----|\n",
      "|  id | ops |\n",
      "|---+-----|\n",
      "| 0 | ~%a : torch.Tensor [#users=0] = placeholder[target=a]~ |\n",
      "| 1 | ~%b : torch.Tensor [#users=0] = placeholder[target=b]~ |\n",
      "\n",
      "\n",
      "\n",
      "\n",
      "** Tracing on a simple case (step 1) :B_block:\n",
      ":PROPERTIES:\n",
      ":BEAMER_env: block\n",
      ":BEAMER_opt: fragile\n",
      ":END:\n",
      "*** C :B_columns:\n",
      ":PROPERTIES:\n",
      ":BEAMER_opt: t\n",
      ":BEAMER_env: columns\n",
      ":END:\n",
      "**** Tracing the bytecode :BMCOL:\n",
      ":PROPERTIES:\n",
      ":BEAMER_col: 0.5\n",
      ":END:\n",
      "\n",
      "\\tiny\n",
      "#+BEGIN_SRC latex\n",
      "\\begin{minted}[highlightlines=2, highlightcolor=pink]{python}\n",
      "  2           0 LOAD_CONST               1 (0)\n",
      "              2 STORE_FAST               2 (a0)\n",
      "\n",
      "  3           4 LOAD_CONST               2 (1)\n",
      "              6 STORE_FAST               3 (a1)\n",
      "\n",
      "  4           8 LOAD_CONST               3 (2)\n",
      "             10 STORE_FAST               4 (a2)\n",
      "\n",
      "  5          12 LOAD_FAST                2 (a0)\n",
      "             14 LOAD_FAST                3 (a1)\n",
      "             16 BINARY_ADD\n",
      "             18 LOAD_FAST                4 (a2)\n",
      "             20 BINARY_ADD\n",
      "             22 STORE_FAST               5 (a3)\n",
      "\n",
      "  6          24 LOAD_FAST                0 (a)\n",
      "             26 LOAD_METHOD              0 (sum)\n",
      "             28 CALL_METHOD              0\n",
      "             30 LOAD_CONST               1 (0)\n",
      "             32 COMPARE_OP               4 (>)\n",
      "             34 POP_JUMP_IF_FALSE       48\n",
      "\n",
      "  7          36 LOAD_FAST                0 (a)\n",
      "             38 LOAD_FAST                1 (b)\n",
      "             40 BINARY_ADD\n",
      "             42 LOAD_FAST                5 (a3)\n",
      "             44 BINARY_ADD\n",
      "             46 RETURN_VALUE\n",
      "\n",
      "  8     >>   48 LOAD_FAST                0 (a)\n",
      "             50 LOAD_FAST                1 (b)\n",
      "             52 BINARY_SUBTRACT\n",
      "             54 RETURN_VALUE\n",
      "\\end{minted}\n",
      "#+END_SRC\n",
      "\n",
      "\n",
      "**** States :B_block:BMCOL:\n",
      ":PROPERTIES:\n",
      ":BEAMER_col: 0.5\n",
      ":BEAMER_opt: t\n",
      ":BEAMER_env: block\n",
      ":END:\n",
      "\n",
      "Store to local variable a0\n",
      "\n",
      "***** Instruction counter\n",
      "\\small\n",
      "\n",
      "2\n",
      "\n",
      "\n",
      "\n",
      "***** Frame stack\n",
      ":PROPERTIES:\n",
      ":BEAMER_env: block\n",
      ":END:\n",
      "\\small\n",
      "|---+--------|\n",
      "| id | values |\n",
      "|---+--------|\n",
      "\n",
      "\n",
      "\n",
      "\n",
      "***** Output graph :B_block:\n",
      ":PROPERTIES:\n",
      ":BEAMER_env: block\n",
      ":END:\n",
      "\\tiny\n",
      "\n",
      "|---+-----|\n",
      "|  id | ops |\n",
      "|---+-----|\n",
      "| 0 | ~%a : torch.Tensor [#users=0] = placeholder[target=a]~ |\n",
      "| 1 | ~%b : torch.Tensor [#users=0] = placeholder[target=b]~ |\n",
      "\n",
      "\n",
      "\n",
      "\n",
      "** Tracing on a simple case (step 2) :B_block:\n",
      ":PROPERTIES:\n",
      ":BEAMER_env: block\n",
      ":BEAMER_opt: fragile\n",
      ":END:\n",
      "*** C :B_columns:\n",
      ":PROPERTIES:\n",
      ":BEAMER_opt: t\n",
      ":BEAMER_env: columns\n",
      ":END:\n",
      "**** Tracing the bytecode :BMCOL:\n",
      ":PROPERTIES:\n",
      ":BEAMER_col: 0.5\n",
      ":END:\n",
      "\n",
      "\\tiny\n",
      "#+BEGIN_SRC latex\n",
      "\\begin{minted}[highlightlines=4, highlightcolor=pink]{python}\n",
      "  2           0 LOAD_CONST               1 (0)\n",
      "              2 STORE_FAST               2 (a0)\n",
      "\n",
      "  3           4 LOAD_CONST               2 (1)\n",
      "              6 STORE_FAST               3 (a1)\n",
      "\n",
      "  4           8 LOAD_CONST               3 (2)\n",
      "             10 STORE_FAST               4 (a2)\n",
      "\n",
      "  5          12 LOAD_FAST                2 (a0)\n",
      "             14 LOAD_FAST                3 (a1)\n",
      "             16 BINARY_ADD\n",
      "             18 LOAD_FAST                4 (a2)\n",
      "             20 BINARY_ADD\n",
      "             22 STORE_FAST               5 (a3)\n",
      "\n",
      "  6          24 LOAD_FAST                0 (a)\n",
      "             26 LOAD_METHOD              0 (sum)\n",
      "             28 CALL_METHOD              0\n",
      "             30 LOAD_CONST               1 (0)\n",
      "             32 COMPARE_OP               4 (>)\n",
      "             34 POP_JUMP_IF_FALSE       48\n",
      "\n",
      "  7          36 LOAD_FAST                0 (a)\n",
      "             38 LOAD_FAST                1 (b)\n",
      "             40 BINARY_ADD\n",
      "             42 LOAD_FAST                5 (a3)\n",
      "             44 BINARY_ADD\n",
      "             46 RETURN_VALUE\n",
      "\n",
      "  8     >>   48 LOAD_FAST                0 (a)\n",
      "             50 LOAD_FAST                1 (b)\n",
      "             52 BINARY_SUBTRACT\n",
      "             54 RETURN_VALUE\n",
      "\\end{minted}\n",
      "#+END_SRC\n",
      "\n",
      "\n",
      "**** States :B_block:BMCOL:\n",
      ":PROPERTIES:\n",
      ":BEAMER_col: 0.5\n",
      ":BEAMER_opt: t\n",
      ":BEAMER_env: block\n",
      ":END:\n",
      "\n",
      "Load a constant, push it on the stack\n",
      "\n",
      "***** Instruction counter\n",
      "\\small\n",
      "\n",
      "4\n",
      "\n",
      "\n",
      "\n",
      "***** Frame stack\n",
      ":PROPERTIES:\n",
      ":BEAMER_env: block\n",
      ":END:\n",
      "\\small\n",
      "|---+--------|\n",
      "| id | values |\n",
      "|---+--------|\n",
      "| 0 | ~ConstantValue(1)~ |\n",
      "\n",
      "\n",
      "\n",
      "***** Output graph :B_block:\n",
      ":PROPERTIES:\n",
      ":BEAMER_env: block\n",
      ":END:\n",
      "\\tiny\n",
      "\n",
      "|---+-----|\n",
      "|  id | ops |\n",
      "|---+-----|\n",
      "| 0 | ~%a : torch.Tensor [#users=0] = placeholder[target=a]~ |\n",
      "| 1 | ~%b : torch.Tensor [#users=0] = placeholder[target=b]~ |\n",
      "\n",
      "\n",
      "\n",
      "\n",
      "** Tracing on a simple case (step 3) :B_block:\n",
      ":PROPERTIES:\n",
      ":BEAMER_env: block\n",
      ":BEAMER_opt: fragile\n",
      ":END:\n",
      "*** C :B_columns:\n",
      ":PROPERTIES:\n",
      ":BEAMER_opt: t\n",
      ":BEAMER_env: columns\n",
      ":END:\n",
      "**** Tracing the bytecode :BMCOL:\n",
      ":PROPERTIES:\n",
      ":BEAMER_col: 0.5\n",
      ":END:\n",
      "\n",
      "\\tiny\n",
      "#+BEGIN_SRC latex\n",
      "\\begin{minted}[highlightlines=5, highlightcolor=pink]{python}\n",
      "  2           0 LOAD_CONST               1 (0)\n",
      "              2 STORE_FAST               2 (a0)\n",
      "\n",
      "  3           4 LOAD_CONST               2 (1)\n",
      "              6 STORE_FAST               3 (a1)\n",
      "\n",
      "  4           8 LOAD_CONST               3 (2)\n",
      "             10 STORE_FAST               4 (a2)\n",
      "\n",
      "  5          12 LOAD_FAST                2 (a0)\n",
      "             14 LOAD_FAST                3 (a1)\n",
      "             16 BINARY_ADD\n",
      "             18 LOAD_FAST                4 (a2)\n",
      "             20 BINARY_ADD\n",
      "             22 STORE_FAST               5 (a3)\n",
      "\n",
      "  6          24 LOAD_FAST                0 (a)\n",
      "             26 LOAD_METHOD              0 (sum)\n",
      "             28 CALL_METHOD              0\n",
      "             30 LOAD_CONST               1 (0)\n",
      "             32 COMPARE_OP               4 (>)\n",
      "             34 POP_JUMP_IF_FALSE       48\n",
      "\n",
      "  7          36 LOAD_FAST                0 (a)\n",
      "             38 LOAD_FAST                1 (b)\n",
      "             40 BINARY_ADD\n",
      "             42 LOAD_FAST                5 (a3)\n",
      "             44 BINARY_ADD\n",
      "             46 RETURN_VALUE\n",
      "\n",
      "  8     >>   48 LOAD_FAST                0 (a)\n",
      "             50 LOAD_FAST                1 (b)\n",
      "             52 BINARY_SUBTRACT\n",
      "             54 RETURN_VALUE\n",
      "\\end{minted}\n",
      "#+END_SRC\n",
      "\n",
      "\n",
      "**** States :B_block:BMCOL:\n",
      ":PROPERTIES:\n",
      ":BEAMER_col: 0.5\n",
      ":BEAMER_opt: t\n",
      ":BEAMER_env: block\n",
      ":END:\n",
      "\n",
      "Store to local variable a1\n",
      "\n",
      "***** Instruction counter\n",
      "\\small\n",
      "\n",
      "6\n",
      "\n",
      "\n",
      "\n",
      "***** Frame stack\n",
      ":PROPERTIES:\n",
      ":BEAMER_env: block\n",
      ":END:\n",
      "\\small\n",
      "|---+--------|\n",
      "| id | values |\n",
      "|---+--------|\n",
      "\n",
      "\n",
      "\n",
      "\n",
      "***** Output graph :B_block:\n",
      ":PROPERTIES:\n",
      ":BEAMER_env: block\n",
      ":END:\n",
      "\\tiny\n",
      "\n",
      "|---+-----|\n",
      "|  id | ops |\n",
      "|---+-----|\n",
      "| 0 | ~%a : torch.Tensor [#users=0] = placeholder[target=a]~ |\n",
      "| 1 | ~%b : torch.Tensor [#users=0] = placeholder[target=b]~ |\n",
      "\n",
      "\n",
      "\n",
      "\n",
      "** Tracing on a simple case (step 4) :B_block:\n",
      ":PROPERTIES:\n",
      ":BEAMER_env: block\n",
      ":BEAMER_opt: fragile\n",
      ":END:\n",
      "*** C :B_columns:\n",
      ":PROPERTIES:\n",
      ":BEAMER_opt: t\n",
      ":BEAMER_env: columns\n",
      ":END:\n",
      "**** Tracing the bytecode :BMCOL:\n",
      ":PROPERTIES:\n",
      ":BEAMER_col: 0.5\n",
      ":END:\n",
      "\n",
      "\\tiny\n",
      "#+BEGIN_SRC latex\n",
      "\\begin{minted}[highlightlines=7, highlightcolor=pink]{python}\n",
      "  2           0 LOAD_CONST               1 (0)\n",
      "              2 STORE_FAST               2 (a0)\n",
      "\n",
      "  3           4 LOAD_CONST               2 (1)\n",
      "              6 STORE_FAST               3 (a1)\n",
      "\n",
      "  4           8 LOAD_CONST               3 (2)\n",
      "             10 STORE_FAST               4 (a2)\n",
      "\n",
      "  5          12 LOAD_FAST                2 (a0)\n",
      "             14 LOAD_FAST                3 (a1)\n",
      "             16 BINARY_ADD\n",
      "             18 LOAD_FAST                4 (a2)\n",
      "             20 BINARY_ADD\n",
      "             22 STORE_FAST               5 (a3)\n",
      "\n",
      "  6          24 LOAD_FAST                0 (a)\n",
      "             26 LOAD_METHOD              0 (sum)\n",
      "             28 CALL_METHOD              0\n",
      "             30 LOAD_CONST               1 (0)\n",
      "             32 COMPARE_OP               4 (>)\n",
      "             34 POP_JUMP_IF_FALSE       48\n",
      "\n",
      "  7          36 LOAD_FAST                0 (a)\n",
      "             38 LOAD_FAST                1 (b)\n",
      "             40 BINARY_ADD\n",
      "             42 LOAD_FAST                5 (a3)\n",
      "             44 BINARY_ADD\n",
      "             46 RETURN_VALUE\n",
      "\n",
      "  8     >>   48 LOAD_FAST                0 (a)\n",
      "             50 LOAD_FAST                1 (b)\n",
      "             52 BINARY_SUBTRACT\n",
      "             54 RETURN_VALUE\n",
      "\\end{minted}\n",
      "#+END_SRC\n",
      "\n",
      "\n",
      "**** States :B_block:BMCOL:\n",
      ":PROPERTIES:\n",
      ":BEAMER_col: 0.5\n",
      ":BEAMER_opt: t\n",
      ":BEAMER_env: block\n",
      ":END:\n",
      "\n",
      "Load a constant, push it on the stack\n",
      "\n",
      "***** Instruction counter\n",
      "\\small\n",
      "\n",
      "8\n",
      "\n",
      "\n",
      "\n",
      "***** Frame stack\n",
      ":PROPERTIES:\n",
      ":BEAMER_env: block\n",
      ":END:\n",
      "\\small\n",
      "|---+--------|\n",
      "| id | values |\n",
      "|---+--------|\n",
      "| 0 | ~ConstantValue(2)~ |\n",
      "\n",
      "\n",
      "\n",
      "***** Output graph :B_block:\n",
      ":PROPERTIES:\n",
      ":BEAMER_env: block\n",
      ":END:\n",
      "\\tiny\n",
      "\n",
      "|---+-----|\n",
      "|  id | ops |\n",
      "|---+-----|\n",
      "| 0 | ~%a : torch.Tensor [#users=0] = placeholder[target=a]~ |\n",
      "| 1 | ~%b : torch.Tensor [#users=0] = placeholder[target=b]~ |\n",
      "\n",
      "\n",
      "\n",
      "\n",
      "** Tracing on a simple case (step 5) :B_block:\n",
      ":PROPERTIES:\n",
      ":BEAMER_env: block\n",
      ":BEAMER_opt: fragile\n",
      ":END:\n",
      "*** C :B_columns:\n",
      ":PROPERTIES:\n",
      ":BEAMER_opt: t\n",
      ":BEAMER_env: columns\n",
      ":END:\n",
      "**** Tracing the bytecode :BMCOL:\n",
      ":PROPERTIES:\n",
      ":BEAMER_col: 0.5\n",
      ":END:\n",
      "\n",
      "\\tiny\n",
      "#+BEGIN_SRC latex\n",
      "\\begin{minted}[highlightlines=8, highlightcolor=pink]{python}\n",
      "  2           0 LOAD_CONST               1 (0)\n",
      "              2 STORE_FAST               2 (a0)\n",
      "\n",
      "  3           4 LOAD_CONST               2 (1)\n",
      "              6 STORE_FAST               3 (a1)\n",
      "\n",
      "  4           8 LOAD_CONST               3 (2)\n",
      "             10 STORE_FAST               4 (a2)\n",
      "\n",
      "  5          12 LOAD_FAST                2 (a0)\n",
      "             14 LOAD_FAST                3 (a1)\n",
      "             16 BINARY_ADD\n",
      "             18 LOAD_FAST                4 (a2)\n",
      "             20 BINARY_ADD\n",
      "             22 STORE_FAST               5 (a3)\n",
      "\n",
      "  6          24 LOAD_FAST                0 (a)\n",
      "             26 LOAD_METHOD              0 (sum)\n",
      "             28 CALL_METHOD              0\n",
      "             30 LOAD_CONST               1 (0)\n",
      "             32 COMPARE_OP               4 (>)\n",
      "             34 POP_JUMP_IF_FALSE       48\n",
      "\n",
      "  7          36 LOAD_FAST                0 (a)\n",
      "             38 LOAD_FAST                1 (b)\n",
      "             40 BINARY_ADD\n",
      "             42 LOAD_FAST                5 (a3)\n",
      "             44 BINARY_ADD\n",
      "             46 RETURN_VALUE\n",
      "\n",
      "  8     >>   48 LOAD_FAST                0 (a)\n",
      "             50 LOAD_FAST                1 (b)\n",
      "             52 BINARY_SUBTRACT\n",
      "             54 RETURN_VALUE\n",
      "\\end{minted}\n",
      "#+END_SRC\n",
      "\n",
      "\n",
      "**** States :B_block:BMCOL:\n",
      ":PROPERTIES:\n",
      ":BEAMER_col: 0.5\n",
      ":BEAMER_opt: t\n",
      ":BEAMER_env: block\n",
      ":END:\n",
      "\n",
      "Store to local variable a2\n",
      "\n",
      "***** Instruction counter\n",
      "\\small\n",
      "\n",
      "10\n",
      "\n",
      "\n",
      "\n",
      "***** Frame stack\n",
      ":PROPERTIES:\n",
      ":BEAMER_env: block\n",
      ":END:\n",
      "\\small\n",
      "|---+--------|\n",
      "| id | values |\n",
      "|---+--------|\n",
      "\n",
      "\n",
      "\n",
      "\n",
      "***** Output graph :B_block:\n",
      ":PROPERTIES:\n",
      ":BEAMER_env: block\n",
      ":END:\n",
      "\\tiny\n",
      "\n",
      "|---+-----|\n",
      "|  id | ops |\n",
      "|---+-----|\n",
      "| 0 | ~%a : torch.Tensor [#users=0] = placeholder[target=a]~ |\n",
      "| 1 | ~%b : torch.Tensor [#users=0] = placeholder[target=b]~ |\n",
      "\n",
      "\n",
      "\n",
      "\n",
      "** Tracing on a simple case (step 6) :B_block:\n",
      ":PROPERTIES:\n",
      ":BEAMER_env: block\n",
      ":BEAMER_opt: fragile\n",
      ":END:\n",
      "*** C :B_columns:\n",
      ":PROPERTIES:\n",
      ":BEAMER_opt: t\n",
      ":BEAMER_env: columns\n",
      ":END:\n",
      "**** Tracing the bytecode :BMCOL:\n",
      ":PROPERTIES:\n",
      ":BEAMER_col: 0.5\n",
      ":END:\n",
      "\n",
      "\\tiny\n",
      "#+BEGIN_SRC latex\n",
      "\\begin{minted}[highlightlines=10, highlightcolor=pink]{python}\n",
      "  2           0 LOAD_CONST               1 (0)\n",
      "              2 STORE_FAST               2 (a0)\n",
      "\n",
      "  3           4 LOAD_CONST               2 (1)\n",
      "              6 STORE_FAST               3 (a1)\n",
      "\n",
      "  4           8 LOAD_CONST               3 (2)\n",
      "             10 STORE_FAST               4 (a2)\n",
      "\n",
      "  5          12 LOAD_FAST                2 (a0)\n",
      "             14 LOAD_FAST                3 (a1)\n",
      "             16 BINARY_ADD\n",
      "             18 LOAD_FAST                4 (a2)\n",
      "             20 BINARY_ADD\n",
      "             22 STORE_FAST               5 (a3)\n",
      "\n",
      "  6          24 LOAD_FAST                0 (a)\n",
      "             26 LOAD_METHOD              0 (sum)\n",
      "             28 CALL_METHOD              0\n",
      "             30 LOAD_CONST               1 (0)\n",
      "             32 COMPARE_OP               4 (>)\n",
      "             34 POP_JUMP_IF_FALSE       48\n",
      "\n",
      "  7          36 LOAD_FAST                0 (a)\n",
      "             38 LOAD_FAST                1 (b)\n",
      "             40 BINARY_ADD\n",
      "             42 LOAD_FAST                5 (a3)\n",
      "             44 BINARY_ADD\n",
      "             46 RETURN_VALUE\n",
      "\n",
      "  8     >>   48 LOAD_FAST                0 (a)\n",
      "             50 LOAD_FAST                1 (b)\n",
      "             52 BINARY_SUBTRACT\n",
      "             54 RETURN_VALUE\n",
      "\\end{minted}\n",
      "#+END_SRC\n",
      "\n",
      "\n",
      "**** States :B_block:BMCOL:\n",
      ":PROPERTIES:\n",
      ":BEAMER_col: 0.5\n",
      ":BEAMER_opt: t\n",
      ":BEAMER_env: block\n",
      ":END:\n",
      "\n",
      "Load a constant, push it on the stack\n",
      "\n",
      "***** Instruction counter\n",
      "\\small\n",
      "\n",
      "12\n",
      "\n",
      "\n",
      "\n",
      "***** Frame stack\n",
      ":PROPERTIES:\n",
      ":BEAMER_env: block\n",
      ":END:\n",
      "\\small\n",
      "|---+--------|\n",
      "| id | values |\n",
      "|---+--------|\n",
      "| 0 | ~ConstantValue(a0)~ |\n",
      "\n",
      "\n",
      "\n",
      "***** Output graph :B_block:\n",
      ":PROPERTIES:\n",
      ":BEAMER_env: block\n",
      ":END:\n",
      "\\tiny\n",
      "\n",
      "|---+-----|\n",
      "|  id | ops |\n",
      "|---+-----|\n",
      "| 0 | ~%a : torch.Tensor [#users=0] = placeholder[target=a]~ |\n",
      "| 1 | ~%b : torch.Tensor [#users=0] = placeholder[target=b]~ |\n",
      "\n",
      "\n",
      "\n",
      "\n",
      "** Tracing on a simple case (step 7) :B_block:\n",
      ":PROPERTIES:\n",
      ":BEAMER_env: block\n",
      ":BEAMER_opt: fragile\n",
      ":END:\n",
      "*** C :B_columns:\n",
      ":PROPERTIES:\n",
      ":BEAMER_opt: t\n",
      ":BEAMER_env: columns\n",
      ":END:\n",
      "**** Tracing the bytecode :BMCOL:\n",
      ":PROPERTIES:\n",
      ":BEAMER_col: 0.5\n",
      ":END:\n",
      "\n",
      "\\tiny\n",
      "#+BEGIN_SRC latex\n",
      "\\begin{minted}[highlightlines=11, highlightcolor=pink]{python}\n",
      "  2           0 LOAD_CONST               1 (0)\n",
      "              2 STORE_FAST               2 (a0)\n",
      "\n",
      "  3           4 LOAD_CONST               2 (1)\n",
      "              6 STORE_FAST               3 (a1)\n",
      "\n",
      "  4           8 LOAD_CONST               3 (2)\n",
      "             10 STORE_FAST               4 (a2)\n",
      "\n",
      "  5          12 LOAD_FAST                2 (a0)\n",
      "             14 LOAD_FAST                3 (a1)\n",
      "             16 BINARY_ADD\n",
      "             18 LOAD_FAST                4 (a2)\n",
      "             20 BINARY_ADD\n",
      "             22 STORE_FAST               5 (a3)\n",
      "\n",
      "  6          24 LOAD_FAST                0 (a)\n",
      "             26 LOAD_METHOD              0 (sum)\n",
      "             28 CALL_METHOD              0\n",
      "             30 LOAD_CONST               1 (0)\n",
      "             32 COMPARE_OP               4 (>)\n",
      "             34 POP_JUMP_IF_FALSE       48\n",
      "\n",
      "  7          36 LOAD_FAST                0 (a)\n",
      "             38 LOAD_FAST                1 (b)\n",
      "             40 BINARY_ADD\n",
      "             42 LOAD_FAST                5 (a3)\n",
      "             44 BINARY_ADD\n",
      "             46 RETURN_VALUE\n",
      "\n",
      "  8     >>   48 LOAD_FAST                0 (a)\n",
      "             50 LOAD_FAST                1 (b)\n",
      "             52 BINARY_SUBTRACT\n",
      "             54 RETURN_VALUE\n",
      "\\end{minted}\n",
      "#+END_SRC\n",
      "\n",
      "\n",
      "**** States :B_block:BMCOL:\n",
      ":PROPERTIES:\n",
      ":BEAMER_col: 0.5\n",
      ":BEAMER_opt: t\n",
      ":BEAMER_env: block\n",
      ":END:\n",
      "\n",
      "Load a constant, push it on the stack\n",
      "\n",
      "***** Instruction counter\n",
      "\\small\n",
      "\n",
      "14\n",
      "\n",
      "\n",
      "\n",
      "***** Frame stack\n",
      ":PROPERTIES:\n",
      ":BEAMER_env: block\n",
      ":END:\n",
      "\\small\n",
      "|---+--------|\n",
      "| id | values |\n",
      "|---+--------|\n",
      "| 0 | ~ConstantValue(a0)~ |\n",
      "| 1 | ~ConstantValue(a1)~ |\n",
      "\n",
      "\n",
      "\n",
      "***** Output graph :B_block:\n",
      ":PROPERTIES:\n",
      ":BEAMER_env: block\n",
      ":END:\n",
      "\\tiny\n",
      "\n",
      "|---+-----|\n",
      "|  id | ops |\n",
      "|---+-----|\n",
      "| 0 | ~%a : torch.Tensor [#users=0] = placeholder[target=a]~ |\n",
      "| 1 | ~%b : torch.Tensor [#users=0] = placeholder[target=b]~ |\n",
      "\n",
      "\n",
      "\n",
      "\n",
      "** Tracing on a simple case (step 8) :B_block:\n",
      ":PROPERTIES:\n",
      ":BEAMER_env: block\n",
      ":BEAMER_opt: fragile\n",
      ":END:\n",
      "*** C :B_columns:\n",
      ":PROPERTIES:\n",
      ":BEAMER_opt: t\n",
      ":BEAMER_env: columns\n",
      ":END:\n",
      "**** Tracing the bytecode :BMCOL:\n",
      ":PROPERTIES:\n",
      ":BEAMER_col: 0.5\n",
      ":END:\n",
      "\n",
      "\\tiny\n",
      "#+BEGIN_SRC latex\n",
      "\\begin{minted}[highlightlines=12, highlightcolor=pink]{python}\n",
      "  2           0 LOAD_CONST               1 (0)\n",
      "              2 STORE_FAST               2 (a0)\n",
      "\n",
      "  3           4 LOAD_CONST               2 (1)\n",
      "              6 STORE_FAST               3 (a1)\n",
      "\n",
      "  4           8 LOAD_CONST               3 (2)\n",
      "             10 STORE_FAST               4 (a2)\n",
      "\n",
      "  5          12 LOAD_FAST                2 (a0)\n",
      "             14 LOAD_FAST                3 (a1)\n",
      "             16 BINARY_ADD\n",
      "             18 LOAD_FAST                4 (a2)\n",
      "             20 BINARY_ADD\n",
      "             22 STORE_FAST               5 (a3)\n",
      "\n",
      "  6          24 LOAD_FAST                0 (a)\n",
      "             26 LOAD_METHOD              0 (sum)\n",
      "             28 CALL_METHOD              0\n",
      "             30 LOAD_CONST               1 (0)\n",
      "             32 COMPARE_OP               4 (>)\n",
      "             34 POP_JUMP_IF_FALSE       48\n",
      "\n",
      "  7          36 LOAD_FAST                0 (a)\n",
      "             38 LOAD_FAST                1 (b)\n",
      "             40 BINARY_ADD\n",
      "             42 LOAD_FAST                5 (a3)\n",
      "             44 BINARY_ADD\n",
      "             46 RETURN_VALUE\n",
      "\n",
      "  8     >>   48 LOAD_FAST                0 (a)\n",
      "             50 LOAD_FAST                1 (b)\n",
      "             52 BINARY_SUBTRACT\n",
      "             54 RETURN_VALUE\n",
      "\\end{minted}\n",
      "#+END_SRC\n",
      "\n",
      "\n",
      "**** States :B_block:BMCOL:\n",
      ":PROPERTIES:\n",
      ":BEAMER_col: 0.5\n",
      ":BEAMER_opt: t\n",
      ":BEAMER_env: block\n",
      ":END:\n",
      "\n",
      "\n",
      "\n",
      "***** Instruction counter\n",
      "\\small\n",
      "\n",
      "16\n",
      "\n",
      "\n",
      "\n",
      "***** Frame stack\n",
      ":PROPERTIES:\n",
      ":BEAMER_env: block\n",
      ":END:\n",
      "\\small\n",
      "|---+--------|\n",
      "| id | values |\n",
      "|---+--------|\n",
      "| 0 | ~ConstantValue(1)~ |\n",
      "\n",
      "\n",
      "\n",
      "***** Output graph :B_block:\n",
      ":PROPERTIES:\n",
      ":BEAMER_env: block\n",
      ":END:\n",
      "\\tiny\n",
      "\n",
      "|---+-----|\n",
      "|  id | ops |\n",
      "|---+-----|\n",
      "| 0 | ~%a : torch.Tensor [#users=0] = placeholder[target=a]~ |\n",
      "| 1 | ~%b : torch.Tensor [#users=0] = placeholder[target=b]~ |\n",
      "\n",
      "\n",
      "\n",
      "\n",
      "** Tracing on a simple case (step 9) :B_block:\n",
      ":PROPERTIES:\n",
      ":BEAMER_env: block\n",
      ":BEAMER_opt: fragile\n",
      ":END:\n",
      "*** C :B_columns:\n",
      ":PROPERTIES:\n",
      ":BEAMER_opt: t\n",
      ":BEAMER_env: columns\n",
      ":END:\n",
      "**** Tracing the bytecode :BMCOL:\n",
      ":PROPERTIES:\n",
      ":BEAMER_col: 0.5\n",
      ":END:\n",
      "\n",
      "\\tiny\n",
      "#+BEGIN_SRC latex\n",
      "\\begin{minted}[highlightlines=13, highlightcolor=pink]{python}\n",
      "  2           0 LOAD_CONST               1 (0)\n",
      "              2 STORE_FAST               2 (a0)\n",
      "\n",
      "  3           4 LOAD_CONST               2 (1)\n",
      "              6 STORE_FAST               3 (a1)\n",
      "\n",
      "  4           8 LOAD_CONST               3 (2)\n",
      "             10 STORE_FAST               4 (a2)\n",
      "\n",
      "  5          12 LOAD_FAST                2 (a0)\n",
      "             14 LOAD_FAST                3 (a1)\n",
      "             16 BINARY_ADD\n",
      "             18 LOAD_FAST                4 (a2)\n",
      "             20 BINARY_ADD\n",
      "             22 STORE_FAST               5 (a3)\n",
      "\n",
      "  6          24 LOAD_FAST                0 (a)\n",
      "             26 LOAD_METHOD              0 (sum)\n",
      "             28 CALL_METHOD              0\n",
      "             30 LOAD_CONST               1 (0)\n",
      "             32 COMPARE_OP               4 (>)\n",
      "             34 POP_JUMP_IF_FALSE       48\n",
      "\n",
      "  7          36 LOAD_FAST                0 (a)\n",
      "             38 LOAD_FAST                1 (b)\n",
      "             40 BINARY_ADD\n",
      "             42 LOAD_FAST                5 (a3)\n",
      "             44 BINARY_ADD\n",
      "             46 RETURN_VALUE\n",
      "\n",
      "  8     >>   48 LOAD_FAST                0 (a)\n",
      "             50 LOAD_FAST                1 (b)\n",
      "             52 BINARY_SUBTRACT\n",
      "             54 RETURN_VALUE\n",
      "\\end{minted}\n",
      "#+END_SRC\n",
      "\n",
      "\n",
      "**** States :B_block:BMCOL:\n",
      ":PROPERTIES:\n",
      ":BEAMER_col: 0.5\n",
      ":BEAMER_opt: t\n",
      ":BEAMER_env: block\n",
      ":END:\n",
      "\n",
      "Load a constant, push it on the stack\n",
      "\n",
      "***** Instruction counter\n",
      "\\small\n",
      "\n",
      "18\n",
      "\n",
      "\n",
      "\n",
      "***** Frame stack\n",
      ":PROPERTIES:\n",
      ":BEAMER_env: block\n",
      ":END:\n",
      "\\small\n",
      "|---+--------|\n",
      "| id | values |\n",
      "|---+--------|\n",
      "| 0 | ~ConstantValue(1)~ |\n",
      "| 1 | ~ConstantValue(a2)~ |\n",
      "\n",
      "\n",
      "\n",
      "***** Output graph :B_block:\n",
      ":PROPERTIES:\n",
      ":BEAMER_env: block\n",
      ":END:\n",
      "\\tiny\n",
      "\n",
      "|---+-----|\n",
      "|  id | ops |\n",
      "|---+-----|\n",
      "| 0 | ~%a : torch.Tensor [#users=0] = placeholder[target=a]~ |\n",
      "| 1 | ~%b : torch.Tensor [#users=0] = placeholder[target=b]~ |\n",
      "\n",
      "\n",
      "\n",
      "\n",
      "** Tracing on a simple case (step 10) :B_block:\n",
      ":PROPERTIES:\n",
      ":BEAMER_env: block\n",
      ":BEAMER_opt: fragile\n",
      ":END:\n",
      "*** C :B_columns:\n",
      ":PROPERTIES:\n",
      ":BEAMER_opt: t\n",
      ":BEAMER_env: columns\n",
      ":END:\n",
      "**** Tracing the bytecode :BMCOL:\n",
      ":PROPERTIES:\n",
      ":BEAMER_col: 0.5\n",
      ":END:\n",
      "\n",
      "\\tiny\n",
      "#+BEGIN_SRC latex\n",
      "\\begin{minted}[highlightlines=14, highlightcolor=pink]{python}\n",
      "  2           0 LOAD_CONST               1 (0)\n",
      "              2 STORE_FAST               2 (a0)\n",
      "\n",
      "  3           4 LOAD_CONST               2 (1)\n",
      "              6 STORE_FAST               3 (a1)\n",
      "\n",
      "  4           8 LOAD_CONST               3 (2)\n",
      "             10 STORE_FAST               4 (a2)\n",
      "\n",
      "  5          12 LOAD_FAST                2 (a0)\n",
      "             14 LOAD_FAST                3 (a1)\n",
      "             16 BINARY_ADD\n",
      "             18 LOAD_FAST                4 (a2)\n",
      "             20 BINARY_ADD\n",
      "             22 STORE_FAST               5 (a3)\n",
      "\n",
      "  6          24 LOAD_FAST                0 (a)\n",
      "             26 LOAD_METHOD              0 (sum)\n",
      "             28 CALL_METHOD              0\n",
      "             30 LOAD_CONST               1 (0)\n",
      "             32 COMPARE_OP               4 (>)\n",
      "             34 POP_JUMP_IF_FALSE       48\n",
      "\n",
      "  7          36 LOAD_FAST                0 (a)\n",
      "             38 LOAD_FAST                1 (b)\n",
      "             40 BINARY_ADD\n",
      "             42 LOAD_FAST                5 (a3)\n",
      "             44 BINARY_ADD\n",
      "             46 RETURN_VALUE\n",
      "\n",
      "  8     >>   48 LOAD_FAST                0 (a)\n",
      "             50 LOAD_FAST                1 (b)\n",
      "             52 BINARY_SUBTRACT\n",
      "             54 RETURN_VALUE\n",
      "\\end{minted}\n",
      "#+END_SRC\n",
      "\n",
      "\n",
      "**** States :B_block:BMCOL:\n",
      ":PROPERTIES:\n",
      ":BEAMER_col: 0.5\n",
      ":BEAMER_opt: t\n",
      ":BEAMER_env: block\n",
      ":END:\n",
      "\n",
      "\n",
      "\n",
      "***** Instruction counter\n",
      "\\small\n",
      "\n",
      "20\n",
      "\n",
      "\n",
      "\n",
      "***** Frame stack\n",
      ":PROPERTIES:\n",
      ":BEAMER_env: block\n",
      ":END:\n",
      "\\small\n",
      "|---+--------|\n",
      "| id | values |\n",
      "|---+--------|\n",
      "| 0 | ~ConstantValue(3)~ |\n",
      "\n",
      "\n",
      "\n",
      "***** Output graph :B_block:\n",
      ":PROPERTIES:\n",
      ":BEAMER_env: block\n",
      ":END:\n",
      "\\tiny\n",
      "\n",
      "|---+-----|\n",
      "|  id | ops |\n",
      "|---+-----|\n",
      "| 0 | ~%a : torch.Tensor [#users=0] = placeholder[target=a]~ |\n",
      "| 1 | ~%b : torch.Tensor [#users=0] = placeholder[target=b]~ |\n",
      "\n",
      "\n",
      "\n",
      "\n",
      "** Tracing on a simple case (step 11) :B_block:\n",
      ":PROPERTIES:\n",
      ":BEAMER_env: block\n",
      ":BEAMER_opt: fragile\n",
      ":END:\n",
      "*** C :B_columns:\n",
      ":PROPERTIES:\n",
      ":BEAMER_opt: t\n",
      ":BEAMER_env: columns\n",
      ":END:\n",
      "**** Tracing the bytecode :BMCOL:\n",
      ":PROPERTIES:\n",
      ":BEAMER_col: 0.5\n",
      ":END:\n",
      "\n",
      "\\tiny\n",
      "#+BEGIN_SRC latex\n",
      "\\begin{minted}[highlightlines=15, highlightcolor=pink]{python}\n",
      "  2           0 LOAD_CONST               1 (0)\n",
      "              2 STORE_FAST               2 (a0)\n",
      "\n",
      "  3           4 LOAD_CONST               2 (1)\n",
      "              6 STORE_FAST               3 (a1)\n",
      "\n",
      "  4           8 LOAD_CONST               3 (2)\n",
      "             10 STORE_FAST               4 (a2)\n",
      "\n",
      "  5          12 LOAD_FAST                2 (a0)\n",
      "             14 LOAD_FAST                3 (a1)\n",
      "             16 BINARY_ADD\n",
      "             18 LOAD_FAST                4 (a2)\n",
      "             20 BINARY_ADD\n",
      "             22 STORE_FAST               5 (a3)\n",
      "\n",
      "  6          24 LOAD_FAST                0 (a)\n",
      "             26 LOAD_METHOD              0 (sum)\n",
      "             28 CALL_METHOD              0\n",
      "             30 LOAD_CONST               1 (0)\n",
      "             32 COMPARE_OP               4 (>)\n",
      "             34 POP_JUMP_IF_FALSE       48\n",
      "\n",
      "  7          36 LOAD_FAST                0 (a)\n",
      "             38 LOAD_FAST                1 (b)\n",
      "             40 BINARY_ADD\n",
      "             42 LOAD_FAST                5 (a3)\n",
      "             44 BINARY_ADD\n",
      "             46 RETURN_VALUE\n",
      "\n",
      "  8     >>   48 LOAD_FAST                0 (a)\n",
      "             50 LOAD_FAST                1 (b)\n",
      "             52 BINARY_SUBTRACT\n",
      "             54 RETURN_VALUE\n",
      "\\end{minted}\n",
      "#+END_SRC\n",
      "\n",
      "\n",
      "**** States :B_block:BMCOL:\n",
      ":PROPERTIES:\n",
      ":BEAMER_col: 0.5\n",
      ":BEAMER_opt: t\n",
      ":BEAMER_env: block\n",
      ":END:\n",
      "\n",
      "\n",
      "\n",
      "***** Instruction counter\n",
      "\\small\n",
      "\n",
      "22\n",
      "\n",
      "\n",
      "\n",
      "***** Frame stack\n",
      ":PROPERTIES:\n",
      ":BEAMER_env: block\n",
      ":END:\n",
      "\\small\n",
      "|---+--------|\n",
      "| id | values |\n",
      "|---+--------|\n",
      "\n",
      "\n",
      "\n",
      "\n",
      "***** Output graph :B_block:\n",
      ":PROPERTIES:\n",
      ":BEAMER_env: block\n",
      ":END:\n",
      "\\tiny\n",
      "\n",
      "|---+-----|\n",
      "|  id | ops |\n",
      "|---+-----|\n",
      "| 0 | ~%a : torch.Tensor [#users=0] = placeholder[target=a]~ |\n",
      "| 1 | ~%b : torch.Tensor [#users=0] = placeholder[target=b]~ |\n",
      "\n",
      "\n",
      "\n",
      "\n",
      "** Tracing on a simple case (step 12) :B_block:\n",
      ":PROPERTIES:\n",
      ":BEAMER_env: block\n",
      ":BEAMER_opt: fragile\n",
      ":END:\n",
      "*** C :B_columns:\n",
      ":PROPERTIES:\n",
      ":BEAMER_opt: t\n",
      ":BEAMER_env: columns\n",
      ":END:\n",
      "**** Tracing the bytecode :BMCOL:\n",
      ":PROPERTIES:\n",
      ":BEAMER_col: 0.5\n",
      ":END:\n",
      "\n",
      "\\tiny\n",
      "#+BEGIN_SRC latex\n",
      "\\begin{minted}[highlightlines=17, highlightcolor=pink]{python}\n",
      "  2           0 LOAD_CONST               1 (0)\n",
      "              2 STORE_FAST               2 (a0)\n",
      "\n",
      "  3           4 LOAD_CONST               2 (1)\n",
      "              6 STORE_FAST               3 (a1)\n",
      "\n",
      "  4           8 LOAD_CONST               3 (2)\n",
      "             10 STORE_FAST               4 (a2)\n",
      "\n",
      "  5          12 LOAD_FAST                2 (a0)\n",
      "             14 LOAD_FAST                3 (a1)\n",
      "             16 BINARY_ADD\n",
      "             18 LOAD_FAST                4 (a2)\n",
      "             20 BINARY_ADD\n",
      "             22 STORE_FAST               5 (a3)\n",
      "\n",
      "  6          24 LOAD_FAST                0 (a)\n",
      "             26 LOAD_METHOD              0 (sum)\n",
      "             28 CALL_METHOD              0\n",
      "             30 LOAD_CONST               1 (0)\n",
      "             32 COMPARE_OP               4 (>)\n",
      "             34 POP_JUMP_IF_FALSE       48\n",
      "\n",
      "  7          36 LOAD_FAST                0 (a)\n",
      "             38 LOAD_FAST                1 (b)\n",
      "             40 BINARY_ADD\n",
      "             42 LOAD_FAST                5 (a3)\n",
      "             44 BINARY_ADD\n",
      "             46 RETURN_VALUE\n",
      "\n",
      "  8     >>   48 LOAD_FAST                0 (a)\n",
      "             50 LOAD_FAST                1 (b)\n",
      "             52 BINARY_SUBTRACT\n",
      "             54 RETURN_VALUE\n",
      "\\end{minted}\n",
      "#+END_SRC\n",
      "\n",
      "\n",
      "**** States :B_block:BMCOL:\n",
      ":PROPERTIES:\n",
      ":BEAMER_col: 0.5\n",
      ":BEAMER_opt: t\n",
      ":BEAMER_env: block\n",
      ":END:\n",
      "\n",
      "Load a tensor, push to stack\n",
      "\n",
      "***** Instruction counter\n",
      "\\small\n",
      "\n",
      "24\n",
      "\n",
      "\n",
      "\n",
      "***** Frame stack\n",
      ":PROPERTIES:\n",
      ":BEAMER_env: block\n",
      ":END:\n",
      "\\small\n",
      "|---+--------|\n",
      "| id | values |\n",
      "|---+--------|\n",
      "| 0 | ~TensorVariable(a)~ |\n",
      "\n",
      "\n",
      "\n",
      "***** Output graph :B_block:\n",
      ":PROPERTIES:\n",
      ":BEAMER_env: block\n",
      ":END:\n",
      "\\tiny\n",
      "\n",
      "|---+-----|\n",
      "|  id | ops |\n",
      "|---+-----|\n",
      "| 0 | ~%a : torch.Tensor [#users=0] = placeholder[target=a]~ |\n",
      "| 1 | ~%b : torch.Tensor [#users=0] = placeholder[target=b]~ |\n",
      "\n",
      "\n",
      "\n",
      "\n",
      "** Tracing on a simple case (step 13) :B_block:\n",
      ":PROPERTIES:\n",
      ":BEAMER_env: block\n",
      ":BEAMER_opt: fragile\n",
      ":END:\n",
      "*** C :B_columns:\n",
      ":PROPERTIES:\n",
      ":BEAMER_opt: t\n",
      ":BEAMER_env: columns\n",
      ":END:\n",
      "**** Tracing the bytecode :BMCOL:\n",
      ":PROPERTIES:\n",
      ":BEAMER_col: 0.5\n",
      ":END:\n",
      "\n",
      "\\tiny\n",
      "#+BEGIN_SRC latex\n",
      "\\begin{minted}[highlightlines=18, highlightcolor=pink]{python}\n",
      "  2           0 LOAD_CONST               1 (0)\n",
      "              2 STORE_FAST               2 (a0)\n",
      "\n",
      "  3           4 LOAD_CONST               2 (1)\n",
      "              6 STORE_FAST               3 (a1)\n",
      "\n",
      "  4           8 LOAD_CONST               3 (2)\n",
      "             10 STORE_FAST               4 (a2)\n",
      "\n",
      "  5          12 LOAD_FAST                2 (a0)\n",
      "             14 LOAD_FAST                3 (a1)\n",
      "             16 BINARY_ADD\n",
      "             18 LOAD_FAST                4 (a2)\n",
      "             20 BINARY_ADD\n",
      "             22 STORE_FAST               5 (a3)\n",
      "\n",
      "  6          24 LOAD_FAST                0 (a)\n",
      "             26 LOAD_METHOD              0 (sum)\n",
      "             28 CALL_METHOD              0\n",
      "             30 LOAD_CONST               1 (0)\n",
      "             32 COMPARE_OP               4 (>)\n",
      "             34 POP_JUMP_IF_FALSE       48\n",
      "\n",
      "  7          36 LOAD_FAST                0 (a)\n",
      "             38 LOAD_FAST                1 (b)\n",
      "             40 BINARY_ADD\n",
      "             42 LOAD_FAST                5 (a3)\n",
      "             44 BINARY_ADD\n",
      "             46 RETURN_VALUE\n",
      "\n",
      "  8     >>   48 LOAD_FAST                0 (a)\n",
      "             50 LOAD_FAST                1 (b)\n",
      "             52 BINARY_SUBTRACT\n",
      "             54 RETURN_VALUE\n",
      "\\end{minted}\n",
      "#+END_SRC\n",
      "\n",
      "\n",
      "**** States :B_block:BMCOL:\n",
      ":PROPERTIES:\n",
      ":BEAMER_col: 0.5\n",
      ":BEAMER_opt: t\n",
      ":BEAMER_env: block\n",
      ":END:\n",
      "\n",
      "\n",
      "\n",
      "***** Instruction counter\n",
      "\\small\n",
      "\n",
      "26\n",
      "\n",
      "\n",
      "\n",
      "***** Frame stack\n",
      ":PROPERTIES:\n",
      ":BEAMER_env: block\n",
      ":END:\n",
      "\\small\n",
      "|---+--------|\n",
      "| id | values |\n",
      "|---+--------|\n",
      "| 0 | ~TensorVariable(a)~ |\n",
      "| 1 | ~GetAttrVariable(TensorVariable(), sum)~ |\n",
      "\n",
      "\n",
      "\n",
      "***** Output graph :B_block:\n",
      ":PROPERTIES:\n",
      ":BEAMER_env: block\n",
      ":END:\n",
      "\\tiny\n",
      "\n",
      "|---+-----|\n",
      "|  id | ops |\n",
      "|---+-----|\n",
      "| 0 | ~%a : torch.Tensor [#users=0] = placeholder[target=a]~ |\n",
      "| 1 | ~%b : torch.Tensor [#users=0] = placeholder[target=b]~ |\n",
      "\n",
      "\n",
      "\n",
      "\n",
      "** Tracing on a simple case (step 14) :B_block:\n",
      ":PROPERTIES:\n",
      ":BEAMER_env: block\n",
      ":BEAMER_opt: fragile\n",
      ":END:\n",
      "*** C :B_columns:\n",
      ":PROPERTIES:\n",
      ":BEAMER_opt: t\n",
      ":BEAMER_env: columns\n",
      ":END:\n",
      "**** Tracing the bytecode :BMCOL:\n",
      ":PROPERTIES:\n",
      ":BEAMER_col: 0.5\n",
      ":END:\n",
      "\n",
      "\\tiny\n",
      "#+BEGIN_SRC latex\n",
      "\\begin{minted}[highlightlines=19, highlightcolor=pink]{python}\n",
      "  2           0 LOAD_CONST               1 (0)\n",
      "              2 STORE_FAST               2 (a0)\n",
      "\n",
      "  3           4 LOAD_CONST               2 (1)\n",
      "              6 STORE_FAST               3 (a1)\n",
      "\n",
      "  4           8 LOAD_CONST               3 (2)\n",
      "             10 STORE_FAST               4 (a2)\n",
      "\n",
      "  5          12 LOAD_FAST                2 (a0)\n",
      "             14 LOAD_FAST                3 (a1)\n",
      "             16 BINARY_ADD\n",
      "             18 LOAD_FAST                4 (a2)\n",
      "             20 BINARY_ADD\n",
      "             22 STORE_FAST               5 (a3)\n",
      "\n",
      "  6          24 LOAD_FAST                0 (a)\n",
      "             26 LOAD_METHOD              0 (sum)\n",
      "             28 CALL_METHOD              0\n",
      "             30 LOAD_CONST               1 (0)\n",
      "             32 COMPARE_OP               4 (>)\n",
      "             34 POP_JUMP_IF_FALSE       48\n",
      "\n",
      "  7          36 LOAD_FAST                0 (a)\n",
      "             38 LOAD_FAST                1 (b)\n",
      "             40 BINARY_ADD\n",
      "             42 LOAD_FAST                5 (a3)\n",
      "             44 BINARY_ADD\n",
      "             46 RETURN_VALUE\n",
      "\n",
      "  8     >>   48 LOAD_FAST                0 (a)\n",
      "             50 LOAD_FAST                1 (b)\n",
      "             52 BINARY_SUBTRACT\n",
      "             54 RETURN_VALUE\n",
      "\\end{minted}\n",
      "#+END_SRC\n",
      "\n",
      "\n",
      "**** States :B_block:BMCOL:\n",
      ":PROPERTIES:\n",
      ":BEAMER_col: 0.5\n",
      ":BEAMER_opt: t\n",
      ":BEAMER_env: block\n",
      ":END:\n",
      "\n",
      "\n",
      "\n",
      "***** Instruction counter\n",
      "\\small\n",
      "\n",
      "28\n",
      "\n",
      "\n",
      "\n",
      "***** Frame stack\n",
      ":PROPERTIES:\n",
      ":BEAMER_env: block\n",
      ":END:\n",
      "\\small\n",
      "|---+--------|\n",
      "| id | values |\n",
      "|---+--------|\n",
      "| 0 | ~TensorVariable()~ |\n",
      "\n",
      "\n",
      "\n",
      "***** Output graph :B_block:\n",
      ":PROPERTIES:\n",
      ":BEAMER_env: block\n",
      ":END:\n",
      "\\tiny\n",
      "\n",
      "|---+-----|\n",
      "|  id | ops |\n",
      "|---+-----|\n",
      "| 0 | ~%a : torch.Tensor [#users=0] = placeholder[target=a]~ |\n",
      "| 1 | ~%b : torch.Tensor [#users=0] = placeholder[target=b]~ |\n",
      "| 2 | ~%sum_1 : [#users=0] = call_method[target=sum](args = (%a,), kwargs = {})~ |\n",
      "\n",
      "\n",
      "\n",
      "\n",
      "** Tracing on a simple case (step 15) :B_block:\n",
      ":PROPERTIES:\n",
      ":BEAMER_env: block\n",
      ":BEAMER_opt: fragile\n",
      ":END:\n",
      "*** C :B_columns:\n",
      ":PROPERTIES:\n",
      ":BEAMER_opt: t\n",
      ":BEAMER_env: columns\n",
      ":END:\n",
      "**** Tracing the bytecode :BMCOL:\n",
      ":PROPERTIES:\n",
      ":BEAMER_col: 0.5\n",
      ":END:\n",
      "\n",
      "\\tiny\n",
      "#+BEGIN_SRC latex\n",
      "\\begin{minted}[highlightlines=20, highlightcolor=pink]{python}\n",
      "  2           0 LOAD_CONST               1 (0)\n",
      "              2 STORE_FAST               2 (a0)\n",
      "\n",
      "  3           4 LOAD_CONST               2 (1)\n",
      "              6 STORE_FAST               3 (a1)\n",
      "\n",
      "  4           8 LOAD_CONST               3 (2)\n",
      "             10 STORE_FAST               4 (a2)\n",
      "\n",
      "  5          12 LOAD_FAST                2 (a0)\n",
      "             14 LOAD_FAST                3 (a1)\n",
      "             16 BINARY_ADD\n",
      "             18 LOAD_FAST                4 (a2)\n",
      "             20 BINARY_ADD\n",
      "             22 STORE_FAST               5 (a3)\n",
      "\n",
      "  6          24 LOAD_FAST                0 (a)\n",
      "             26 LOAD_METHOD              0 (sum)\n",
      "             28 CALL_METHOD              0\n",
      "             30 LOAD_CONST               1 (0)\n",
      "             32 COMPARE_OP               4 (>)\n",
      "             34 POP_JUMP_IF_FALSE       48\n",
      "\n",
      "  7          36 LOAD_FAST                0 (a)\n",
      "             38 LOAD_FAST                1 (b)\n",
      "             40 BINARY_ADD\n",
      "             42 LOAD_FAST                5 (a3)\n",
      "             44 BINARY_ADD\n",
      "             46 RETURN_VALUE\n",
      "\n",
      "  8     >>   48 LOAD_FAST                0 (a)\n",
      "             50 LOAD_FAST                1 (b)\n",
      "             52 BINARY_SUBTRACT\n",
      "             54 RETURN_VALUE\n",
      "\\end{minted}\n",
      "#+END_SRC\n",
      "\n",
      "\n",
      "**** States :B_block:BMCOL:\n",
      ":PROPERTIES:\n",
      ":BEAMER_col: 0.5\n",
      ":BEAMER_opt: t\n",
      ":BEAMER_env: block\n",
      ":END:\n",
      "\n",
      "\n",
      "\n",
      "***** Instruction counter\n",
      "\\small\n",
      "\n",
      "30\n",
      "\n",
      "\n",
      "\n",
      "***** Frame stack\n",
      ":PROPERTIES:\n",
      ":BEAMER_env: block\n",
      ":END:\n",
      "\\small\n",
      "|---+--------|\n",
      "| id | values |\n",
      "|---+--------|\n",
      "| 0 | ~TensorVariable()~ |\n",
      "| 1 | ~ConstantValue(0)~ |\n",
      "\n",
      "\n",
      "\n",
      "***** Output graph :B_block:\n",
      ":PROPERTIES:\n",
      ":BEAMER_env: block\n",
      ":END:\n",
      "\\tiny\n",
      "\n",
      "|---+-----|\n",
      "|  id | ops |\n",
      "|---+-----|\n",
      "| 0 | ~%a : torch.Tensor [#users=0] = placeholder[target=a]~ |\n",
      "| 1 | ~%b : torch.Tensor [#users=0] = placeholder[target=b]~ |\n",
      "| 2 | ~%sum_1 : [#users=0] = call_method[target=sum](args = (%a,), kwargs = {})~ |\n",
      "\n",
      "\n",
      "\n",
      "\n",
      "** Tracing on a simple case (step 16) :B_block:\n",
      ":PROPERTIES:\n",
      ":BEAMER_env: block\n",
      ":BEAMER_opt: fragile\n",
      ":END:\n",
      "*** C :B_columns:\n",
      ":PROPERTIES:\n",
      ":BEAMER_opt: t\n",
      ":BEAMER_env: columns\n",
      ":END:\n",
      "**** Tracing the bytecode :BMCOL:\n",
      ":PROPERTIES:\n",
      ":BEAMER_col: 0.5\n",
      ":END:\n",
      "\n",
      "\\tiny\n",
      "#+BEGIN_SRC latex\n",
      "\\begin{minted}[highlightlines=21, highlightcolor=pink]{python}\n",
      "  2           0 LOAD_CONST               1 (0)\n",
      "              2 STORE_FAST               2 (a0)\n",
      "\n",
      "  3           4 LOAD_CONST               2 (1)\n",
      "              6 STORE_FAST               3 (a1)\n",
      "\n",
      "  4           8 LOAD_CONST               3 (2)\n",
      "             10 STORE_FAST               4 (a2)\n",
      "\n",
      "  5          12 LOAD_FAST                2 (a0)\n",
      "             14 LOAD_FAST                3 (a1)\n",
      "             16 BINARY_ADD\n",
      "             18 LOAD_FAST                4 (a2)\n",
      "             20 BINARY_ADD\n",
      "             22 STORE_FAST               5 (a3)\n",
      "\n",
      "  6          24 LOAD_FAST                0 (a)\n",
      "             26 LOAD_METHOD              0 (sum)\n",
      "             28 CALL_METHOD              0\n",
      "             30 LOAD_CONST               1 (0)\n",
      "             32 COMPARE_OP               4 (>)\n",
      "             34 POP_JUMP_IF_FALSE       48\n",
      "\n",
      "  7          36 LOAD_FAST                0 (a)\n",
      "             38 LOAD_FAST                1 (b)\n",
      "             40 BINARY_ADD\n",
      "             42 LOAD_FAST                5 (a3)\n",
      "             44 BINARY_ADD\n",
      "             46 RETURN_VALUE\n",
      "\n",
      "  8     >>   48 LOAD_FAST                0 (a)\n",
      "             50 LOAD_FAST                1 (b)\n",
      "             52 BINARY_SUBTRACT\n",
      "             54 RETURN_VALUE\n",
      "\\end{minted}\n",
      "#+END_SRC\n",
      "\n",
      "\n",
      "**** States :B_block:BMCOL:\n",
      ":PROPERTIES:\n",
      ":BEAMER_col: 0.5\n",
      ":BEAMER_opt: t\n",
      ":BEAMER_env: block\n",
      ":END:\n",
      "\n",
      "\n",
      "\n",
      "***** Instruction counter\n",
      "\\small\n",
      "\n",
      "32\n",
      "\n",
      "\n",
      "\n",
      "***** Frame stack\n",
      ":PROPERTIES:\n",
      ":BEAMER_env: block\n",
      ":END:\n",
      "\\small\n",
      "|---+--------|\n",
      "| id | values |\n",
      "|---+--------|\n",
      "| 0 | ~TensorVariable()~ |\n",
      "\n",
      "\n",
      "\n",
      "***** Output graph :B_block:\n",
      ":PROPERTIES:\n",
      ":BEAMER_env: block\n",
      ":END:\n",
      "\\tiny\n",
      "\n",
      "|---+-----|\n",
      "|  id | ops |\n",
      "|---+-----|\n",
      "| 0 | ~%a : torch.Tensor [#users=0] = placeholder[target=a]~ |\n",
      "| 1 | ~%b : torch.Tensor [#users=0] = placeholder[target=b]~ |\n",
      "| 2 | ~%sum_1 : [#users=0] = call_method[target=sum](args = (%a,), kwargs = {})~ |\n",
      "| 3 | ~%gt : [#users=0] = call_method[target=gt](args = (%sum_1, 0), kwargs = {})~ |\n",
      "\n",
      "\n",
      "\n",
      "\n",
      "** Tracing on a simple case (step 17) :B_block:\n",
      ":PROPERTIES:\n",
      ":BEAMER_env: block\n",
      ":BEAMER_opt: fragile\n",
      ":END:\n",
      "*** C :B_columns:\n",
      ":PROPERTIES:\n",
      ":BEAMER_opt: t\n",
      ":BEAMER_env: columns\n",
      ":END:\n",
      "**** Tracing the bytecode :BMCOL:\n",
      ":PROPERTIES:\n",
      ":BEAMER_col: 0.5\n",
      ":END:\n",
      "\n",
      "\\tiny\n",
      "#+BEGIN_SRC latex\n",
      "\\begin{minted}[highlightlines=22, highlightcolor=pink]{python}\n",
      "  2           0 LOAD_CONST               1 (0)\n",
      "              2 STORE_FAST               2 (a0)\n",
      "\n",
      "  3           4 LOAD_CONST               2 (1)\n",
      "              6 STORE_FAST               3 (a1)\n",
      "\n",
      "  4           8 LOAD_CONST               3 (2)\n",
      "             10 STORE_FAST               4 (a2)\n",
      "\n",
      "  5          12 LOAD_FAST                2 (a0)\n",
      "             14 LOAD_FAST                3 (a1)\n",
      "             16 BINARY_ADD\n",
      "             18 LOAD_FAST                4 (a2)\n",
      "             20 BINARY_ADD\n",
      "             22 STORE_FAST               5 (a3)\n",
      "\n",
      "  6          24 LOAD_FAST                0 (a)\n",
      "             26 LOAD_METHOD              0 (sum)\n",
      "             28 CALL_METHOD              0\n",
      "             30 LOAD_CONST               1 (0)\n",
      "             32 COMPARE_OP               4 (>)\n",
      "             34 POP_JUMP_IF_FALSE       48\n",
      "\n",
      "  7          36 LOAD_FAST                0 (a)\n",
      "             38 LOAD_FAST                1 (b)\n",
      "             40 BINARY_ADD\n",
      "             42 LOAD_FAST                5 (a3)\n",
      "             44 BINARY_ADD\n",
      "             46 RETURN_VALUE\n",
      "\n",
      "  8     >>   48 LOAD_FAST                0 (a)\n",
      "             50 LOAD_FAST                1 (b)\n",
      "             52 BINARY_SUBTRACT\n",
      "             54 RETURN_VALUE\n",
      "\\end{minted}\n",
      "#+END_SRC\n",
      "\n",
      "\n",
      "**** States :B_block:BMCOL:\n",
      ":PROPERTIES:\n",
      ":BEAMER_col: 0.5\n",
      ":BEAMER_opt: t\n",
      ":BEAMER_env: block\n",
      ":END:\n",
      "\n",
      "TensorVariable as condition, trigger compile subgraph\n",
      "Follows the heuristics of ~generic_jump()~\n",
      "\n",
      "***** Instruction counter\n",
      "\\small\n",
      "\n",
      "34\n",
      "\n",
      "\n",
      "\n",
      "***** Frame stack\n",
      ":PROPERTIES:\n",
      ":BEAMER_env: block\n",
      ":END:\n",
      "\\small\n",
      "|---+--------|\n",
      "| id | values |\n",
      "|---+--------|\n",
      "\n",
      "\n",
      "\n",
      "\n",
      "***** Output graph :B_block:\n",
      ":PROPERTIES:\n",
      ":BEAMER_env: block\n",
      ":END:\n",
      "\\tiny\n",
      "\n",
      "|---+-----|\n",
      "|  id | ops |\n",
      "|---+-----|\n",
      "\n",
      "\n",
      "\n",
      "\n",
      "\n"
     ]
    }
   ],
   "source": [
    "for record in records:\n",
    "    print(get_block(record))"
   ]
  },
  {
   "cell_type": "code",
   "execution_count": null,
   "metadata": {},
   "outputs": [],
   "source": []
  },
  {
   "cell_type": "code",
   "execution_count": null,
   "metadata": {},
   "outputs": [],
   "source": []
  },
  {
   "cell_type": "code",
   "execution_count": null,
   "metadata": {},
   "outputs": [],
   "source": []
  }
 ],
 "metadata": {
  "kernelspec": {
   "display_name": "newenv2",
   "language": "python",
   "name": "python3"
  },
  "language_info": {
   "codemirror_mode": {
    "name": "ipython",
    "version": 3
   },
   "file_extension": ".py",
   "mimetype": "text/x-python",
   "name": "python",
   "nbconvert_exporter": "python",
   "pygments_lexer": "ipython3",
   "version": "3.8.10"
  },
  "orig_nbformat": 4,
  "vscode": {
   "interpreter": {
    "hash": "79b3c643fceffa1ffebbbec8e48bcead3967abe49c79586407a5e0726120fadf"
   }
  }
 },
 "nbformat": 4,
 "nbformat_minor": 2
}
